parking.v
module parking #(
  parameter UNI_CAPACITY = 500,
  parameter MISC_CAPACITY = 200,
  parameter STEP = 50
) (
  input wire car_entered,
  input wire is_uni_car_entered,
  input wire car_exited,
  input wire is_uni_car_exited,
  input wire clk,
  input wire [5:0] hour,
  input wire enabled,
  output reg [9:0] uni_parked_car,
  output reg [9:0] parked_car,
  output reg [9:0] uni_vacated_space,
  output reg [9:0] vacated_space,
  output wire uni_is_vacated_space,
  output wire is_vacated_space,
  output reg fault
);

  initial begin
    uni_parked_car = 0;
    parked_car = 0;
    fault = 0;
  end

  always @(posedge clk) begin
    if (enabled) begin

      if (car_entered) begin
        if (is_uni_car_entered && uni_vacated_space > 0) begin
          uni_parked_car = uni_parked_car + 1;
        end else if (!is_uni_car_entered && vacated_space > 0) begin
          parked_car = parked_car + 1;
        end
      end

      if (car_exited) begin
        if (is_uni_car_exited && uni_parked_car > 0) begin
          uni_parked_car = uni_parked_car - 1;
        end else if (!is_uni_car_exited && parked_car > 0) begin
          parked_car = parked_car - 1;
        end
      end

      if (hour >= 8 && hour < 13) begin
        uni_vacated_space <= UNI_CAPACITY - uni_parked_car;
        vacated_space <= MISC_CAPACITY - parked_car;
      end else if (hour >= 13 && hour < 16) begin
        uni_vacated_space <= UNI_CAPACITY - (hour - 12) * STEP - uni_parked_car;
        vacated_space <= MISC_CAPACITY + (hour - 12) * STEP - parked_car;
      end else if (hour >= 16) begin
        uni_vacated_space <= MISC_CAPACITY - uni_parked_car;
        vacated_space <= UNI_CAPACITY - parked_car;
      end


      if ((hour >= 13 && hour < 16 && UNI_CAPACITY < (hour - 12) * STEP + uni_parked_car) ||
          (hour >= 16 && (MISC_CAPACITY < uni_parked_car || UNI_CAPACITY < parked_car))) begin
        fault <= 1;
      end else begin
        fault <= 0;
      end
    end
  end

  assign uni_is_vacated_space = uni_vacated_space > 0;
  assign is_vacated_space = vacated_space > 0;

endmodule

parking_tb.v
module parking_tb;
  parameter UNI_CAPACITY = 500;
  parameter MISC_CAPACITY = 200;
  parameter STEP = 50;

  reg car_entered;
  reg is_uni_car_entered;
  reg car_exited;
  reg is_uni_car_exited;
  reg clk;
  reg [5:0] hour;
  reg enabled;

  wire [9:0] uni_parked_car;
  wire [9:0] parked_car;
  wire [9:0] uni_vacated_space;
  wire [9:0] vacated_space;
  wire uni_is_vacated_space;
  wire is_vacated_space;
  wire fault;

  parking #(
    .UNI_CAPACITY(UNI_CAPACITY),
    .MISC_CAPACITY(MISC_CAPACITY),
    .STEP(STEP)
  ) uut (
    .car_entered(car_entered),
    .is_uni_car_entered(is_uni_car_entered),
    .car_exited(car_exited),
    .is_uni_car_exited(is_uni_car_exited),
    .clk(clk),
    .hour(hour),
    .enabled(enabled),
    .uni_parked_car(uni_parked_car),
    .parked_car(parked_car),
    .uni_vacated_space(uni_vacated_space),
    .vacated_space(vacated_space),
    .uni_is_vacated_space(uni_is_vacated_space),
    .is_vacated_space(is_vacated_space),
    .fault(fault)
  );

  initial begin
    clk = 0;
    forever #5 clk = ~clk;
  end

  initial begin
    enabled = 1;
    hour = 8;
    car_entered = 0;
    is_uni_car_entered = 0;
    car_exited = 0;
    is_uni_car_exited = 0;

    $dumpfile("parking_tb.vcd");
    $dumpvars(0, parking_tb);

    $monitor("Time: %0t | Hour: %0d | Car Entered: %0b | Uni Car Entered: %0b | Car Exited: %0b | Uni Car Exited: %0b | Uni Parked Car: %0d | Parked Car: %0d | Uni Vacated Space: %0d | Vacated Space: %0d | uni_is_vacated_space: %0b | is_vacated_space: %0b | Fault: %0b", 
             $time, hour, car_entered, is_uni_car_entered, car_exited, is_uni_car_exited, uni_parked_car, parked_car, uni_vacated_space, vacated_space, uni_is_vacated_space, is_vacated_space, fault);

    // hour = 8:00
    repeat (50) begin
      #10 car_entered = $random % 2;
      is_uni_car_entered = $random % 2;
      car_exited = $random % 2;
      is_uni_car_exited = $random % 2;
    end

    // advance to 13:00
    hour = 13;
    repeat (50) begin
      #10 car_entered = $random % 2;
      is_uni_car_entered = $random % 2;
      car_exited = $random % 2;
      is_uni_car_exited = $random % 2;
    end
    
    // advance to 15:00
    hour = 15;
    repeat (10) begin
      #10 car_entered = $random % 2;
      is_uni_car_entered = $random % 2;
      car_exited = $random % 2;
      is_uni_car_exited = $random % 2;
    end

    // advance to 17:00
    hour = 17;
    // fill up the university section of the parking
    repeat (200) begin
      #10 car_entered = 1;
      is_uni_car_entered = 1;
      car_exited = 0;
      is_uni_car_exited = 0;
    end

    // Finish simulation
    #20 $finish;
  end
endmodule

parking_tb.vcd
$date
	Wed Jun 26 21:51:06 2024
$end
$version
	Icarus Verilog
$end
$timescale
	1s
$end
$scope module parking_tb $end
$var wire 10 ! vacated_space [9:0] $end
$var wire 10 " uni_vacated_space [9:0] $end
$var wire 10 # uni_parked_car [9:0] $end
$var wire 1 $ uni_is_vacated_space $end
$var wire 10 % parked_car [9:0] $end
$var wire 1 & is_vacated_space $end
$var wire 1 ' fault $end
$var parameter 32 ( MISC_CAPACITY $end
$var parameter 32 ) STEP $end
$var parameter 32 * UNI_CAPACITY $end
$var reg 1 + car_entered $end
$var reg 1 , car_exited $end
$var reg 1 - clk $end
$var reg 1 . enabled $end
$var reg 6 / hour [5:0] $end
$var reg 1 0 is_uni_car_entered $end
$var reg 1 1 is_uni_car_exited $end
$scope module uut $end
$var wire 1 + car_entered $end
$var wire 1 , car_exited $end
$var wire 1 - clk $end
$var wire 1 . enabled $end
$var wire 6 2 hour [5:0] $end
$var wire 1 0 is_uni_car_entered $end
$var wire 1 1 is_uni_car_exited $end
$var wire 1 $ uni_is_vacated_space $end
$var wire 1 & is_vacated_space $end
$var parameter 32 3 MISC_CAPACITY $end
$var parameter 32 4 STEP $end
$var parameter 32 5 UNI_CAPACITY $end
$var reg 1 ' fault $end
$var reg 10 6 parked_car [9:0] $end
$var reg 10 7 uni_parked_car [9:0] $end
$var reg 10 8 uni_vacated_space [9:0] $end
$var reg 10 9 vacated_space [9:0] $end
$upscope $end
$upscope $end
$enddefinitions $end
$comment Show the parameter values. $end
$dumpall
b111110100 5
b110010 4
b11001000 3
b111110100 *
b110010 )
b11001000 (
$end
#0
$dumpvars
bx 9
bx 8
b0 7
b0 6
b1000 2
01
00
b1000 /
1.
0-
0,
0+
0'
x&
b0 %
x$
b0 #
bx "
bx !
$end
#5
1&
b11001000 !
b11001000 9
1$
b111110100 "
b111110100 8
1-
#10
0-
11
1,
10
#15
1-
#20
0-
01
1+
#25
b111110011 "
b111110011 8
b1 #
b1 7
1-
#30
0-
11
0,
#35
b111110010 "
b111110010 8
b10 #
b10 7
1-
#40
0-
01
1,
00
#45
b0 %
b0 6
1-
#50
0-
11
#55
b11000111 !
b11000111 9
b111110011 "
b111110011 8
b1 #
b1 7
b1 %
b1 6
1-
#60
0-
01
0,
10
0+
#65
1-
#70
0-
11
#75
1-
#80
0-
01
1,
1+
#85
b11001000 !
b11001000 9
b111110010 "
b111110010 8
b0 %
b0 6
b10 #
b10 7
1-
#90
0-
11
0,
00
0+
#95
1-
#100
0-
1,
10
#105
b111110011 "
b111110011 8
b1 #
b1 7
1-
#110
0-
01
0,
1+
#115
b111110010 "
b111110010 8
b10 #
b10 7
1-
#120
0-
1,
#125
b111110001 "
b111110001 8
b11 #
b11 7
1-
#130
0-
0,
00
0+
#135
1-
#140
0-
11
1+
#145
b11000111 !
b11000111 9
b1 %
b1 6
1-
#150
0-
01
#155
b11000110 !
b11000110 9
b10 %
b10 6
1-
#160
0-
11
1,
0+
#165
b111110010 "
b111110010 8
b10 #
b10 7
1-
#170
0-
01
10
1+
#175
b11000111 !
b11000111 9
b111110001 "
b111110001 8
b1 %
b1 6
b11 #
b11 7
1-
#180
0-
11
0+
#185
b111110010 "
b111110010 8
b10 #
b10 7
1-
#190
0-
00
#195
b111110011 "
b111110011 8
b1 #
b1 7
1-
#200
0-
01
10
#205
b11001000 !
b11001000 9
b0 %
b0 6
1-
#210
0-
1+
#215
b111110010 "
b111110010 8
b10 #
b10 7
1-
#220
0-
0,
#225
b111110001 "
b111110001 8
b11 #
b11 7
1-
#230
0-
11
1,
00
0+
#235
b111110010 "
b111110010 8
b10 #
b10 7
1-
#240
0-
#245
b111110011 "
b111110011 8
b1 #
b1 7
1-
#250
0-
01
10
1+
#255
b111110010 "
b111110010 8
b10 #
b10 7
1-
#260
0-
#265
b111110001 "
b111110001 8
b11 #
b11 7
1-
#270
0-
0,
00
0+
#275
1-
#280
0-
11
1,
#285
b111110010 "
b111110010 8
b10 #
b10 7
1-
#290
0-
01
10
1+
#295
b111110001 "
b111110001 8
b11 #
b11 7
1-
#300
0-
0,
#305
b111110000 "
b111110000 8
b100 #
b100 7
1-
#310
0-
11
#315
b111101111 "
b111101111 8
b101 #
b101 7
1-
#320
0-
01
1,
#325
b111101110 "
b111101110 8
b110 #
b110 7
1-
#330
0-
00
0+
#335
1-
#340
0-
11
#345
b111101111 "
b111101111 8
b101 #
b101 7
1-
#350
0-
01
#355
1-
#360
0-
#365
1-
#370
0-
11
0,
10
#375
1-
#380
0-
1,
1+
#385
b101 #
b101 7
1-
#390
0-
0,
00
0+
#395
1-
#400
0-
1,
#405
b111110000 "
b111110000 8
b100 #
b100 7
1-
#410
0-
0,
#415
1-
#420
0-
01
1+
#425
b11000111 !
b11000111 9
b1 %
b1 6
1-
#430
0-
10
#435
b111101111 "
b111101111 8
b101 #
b101 7
1-
#440
0-
0+
#445
1-
#450
0-
00
1+
#455
b11000110 !
b11000110 9
b10 %
b10 6
1-
#460
0-
11
1,
#465
b11000101 !
b11000101 9
b111110000 "
b111110000 8
b100 #
b100 7
b11 %
b11 6
1-
#470
0-
01
0,
0+
#475
1-
#480
0-
1+
#485
b11000100 !
b11000100 9
b100 %
b100 6
1-
#490
0-
11
1,
10
0+
#495
b111110001 "
b111110001 8
b11 #
b11 7
1-
#500
0-
b1101 /
b1101 2
#505
b11110110 !
b11110110 9
b111000000 "
b111000000 8
b10 #
b10 7
1-
#510
0-
00
#515
b111000001 "
b111000001 8
b1 #
b1 7
1-
#520
0-
01
10
1+
#525
b11110111 !
b11110111 9
b111000000 "
b111000000 8
b11 %
b11 6
b10 #
b10 7
1-
#530
0-
0,
#535
b110111111 "
b110111111 8
b11 #
b11 7
1-
#540
0-
11
1,
00
0+
#545
b111000000 "
b111000000 8
b10 #
b10 7
1-
#550
0-
01
#555
b11111000 !
b11111000 9
b10 %
b10 6
1-
#560
0-
0,
10
#565
1-
#570
0-
11
00
1+
#575
b11110111 !
b11110111 9
b11 %
b11 6
1-
#580
0-
01
10
#585
b110111111 "
b110111111 8
b11 #
b11 7
1-
#590
0-
0+
#595
1-
#600
0-
00
1+
#605
b11110110 !
b11110110 9
b100 %
b100 6
1-
#610
0-
10
0+
#615
1-
#620
0-
1,
#625
b11110111 !
b11110111 9
b11 %
b11 6
1-
#630
0-
11
1+
#635
b11 #
b11 7
1-
#640
0-
0+
#645
b111000000 "
b111000000 8
b10 #
b10 7
1-
#650
0-
01
00
#655
b11111000 !
b11111000 9
b10 %
b10 6
1-
#660
0-
10
#665
b11111001 !
b11111001 9
b1 %
b1 6
1-
#670
0-
0,
#675
1-
#680
0-
11
1,
00
1+
#685
b11111000 !
b11111000 9
b111000001 "
b111000001 8
b1 #
b1 7
b10 %
b10 6
1-
#690
0-
0,
10
0+
#695
1-
#700
0-
01
1,
00
#705
b11111001 !
b11111001 9
b1 %
b1 6
1-
#710
0-
11
#715
b111000010 "
b111000010 8
b0 #
b0 7
1-
#720
0-
01
10
1+
#725
b11111010 !
b11111010 9
b111000001 "
b111000001 8
b0 %
b0 6
b1 #
b1 7
1-
#730
0-
#735
b111000000 "
b111000000 8
b10 #
b10 7
1-
#740
0-
0,
00
0+
#745
1-
#750
0-
11
1,
10
#755
b111000001 "
b111000001 8
b1 #
b1 7
1-
#760
0-
1+
#765
b1 #
b1 7
1-
#770
0-
0+
#775
b111000010 "
b111000010 8
b0 #
b0 7
1-
#780
0-
1+
#785
b0 #
b0 7
1-
#790
0-
0,
00
#795
b11111001 !
b11111001 9
b1 %
b1 6
1-
#800
0-
01
#805
b11111000 !
b11111000 9
b10 %
b10 6
1-
#810
0-
10
0+
#815
1-
#820
0-
00
#825
1-
#830
0-
11
1+
#835
b11110111 !
b11110111 9
b11 %
b11 6
1-
#840
0-
01
0+
#845
1-
#850
0-
11
1,
10
1+
#855
b0 #
b0 7
1-
#860
0-
00
#865
b11110110 !
b11110110 9
b100 %
b100 6
1-
#870
0-
01
#875
b100 %
b100 6
1-
#880
0-
10
0+
#885
b11110111 !
b11110111 9
b11 %
b11 6
1-
#890
0-
11
0,
00
1+
#895
b11110110 !
b11110110 9
b100 %
b100 6
1-
#900
0-
01
0+
#905
1-
#910
0-
11
1,
10
1+
#915
b0 #
b0 7
1-
#920
0-
0+
#925
1-
#930
0-
1+
#935
b0 #
b0 7
1-
#940
0-
0,
0+
#945
1-
#950
0-
01
1,
00
#955
b11110111 !
b11110111 9
b11 %
b11 6
1-
#960
0-
0,
#965
1-
#970
0-
1+
#975
b11110110 !
b11110110 9
b100 %
b100 6
1-
#980
0-
11
0+
#985
1-
#990
0-
01
10
#995
1-
#1000
0-
b1111 /
b1111 2
11
1,
00
1+
#1005
b101011001 !
b101011001 9
b101011110 "
b101011110 8
b101 %
b101 6
1-
#1010
0-
0,
10
0+
#1015
1-
#1020
0-
01
00
#1025
1-
#1030
0-
1,
1+
#1035
b101 %
b101 6
1-
#1040
0-
11
0,
10
#1045
b101011101 "
b101011101 8
b1 #
b1 7
1-
#1050
0-
1,
0+
#1055
b101011110 "
b101011110 8
b0 #
b0 7
1-
#1060
0-
01
#1065
b101011010 !
b101011010 9
b100 %
b100 6
1-
#1070
0-
#1075
b101011011 !
b101011011 9
b11 %
b11 6
1-
#1080
0-
#1085
b101011100 !
b101011100 9
b10 %
b10 6
1-
#1090
0-
0,
#1095
1-
#1100
0-
b10001 /
b10001 2
1+
#1105
b111110010 !
b111110010 9
b11000111 "
b11000111 8
b1 #
b1 7
1-
#1110
0-
#1115
b11000110 "
b11000110 8
b10 #
b10 7
1-
#1120
0-
#1125
b11000101 "
b11000101 8
b11 #
b11 7
1-
#1130
0-
#1135
b11000100 "
b11000100 8
b100 #
b100 7
1-
#1140
0-
#1145
b11000011 "
b11000011 8
b101 #
b101 7
1-
#1150
0-
#1155
b11000010 "
b11000010 8
b110 #
b110 7
1-
#1160
0-
#1165
b11000001 "
b11000001 8
b111 #
b111 7
1-
#1170
0-
#1175
b11000000 "
b11000000 8
b1000 #
b1000 7
1-
#1180
0-
#1185
b10111111 "
b10111111 8
b1001 #
b1001 7
1-
#1190
0-
#1195
b10111110 "
b10111110 8
b1010 #
b1010 7
1-
#1200
0-
#1205
b10111101 "
b10111101 8
b1011 #
b1011 7
1-
#1210
0-
#1215
b10111100 "
b10111100 8
b1100 #
b1100 7
1-
#1220
0-
#1225
b10111011 "
b10111011 8
b1101 #
b1101 7
1-
#1230
0-
#1235
b10111010 "
b10111010 8
b1110 #
b1110 7
1-
#1240
0-
#1245
b10111001 "
b10111001 8
b1111 #
b1111 7
1-
#1250
0-
#1255
b10111000 "
b10111000 8
b10000 #
b10000 7
1-
#1260
0-
#1265
b10110111 "
b10110111 8
b10001 #
b10001 7
1-
#1270
0-
#1275
b10110110 "
b10110110 8
b10010 #
b10010 7
1-
#1280
0-
#1285
b10110101 "
b10110101 8
b10011 #
b10011 7
1-
#1290
0-
#1295
b10110100 "
b10110100 8
b10100 #
b10100 7
1-
#1300
0-
#1305
b10110011 "
b10110011 8
b10101 #
b10101 7
1-
#1310
0-
#1315
b10110010 "
b10110010 8
b10110 #
b10110 7
1-
#1320
0-
#1325
b10110001 "
b10110001 8
b10111 #
b10111 7
1-
#1330
0-
#1335
b10110000 "
b10110000 8
b11000 #
b11000 7
1-
#1340
0-
#1345
b10101111 "
b10101111 8
b11001 #
b11001 7
1-
#1350
0-
#1355
b10101110 "
b10101110 8
b11010 #
b11010 7
1-
#1360
0-
#1365
b10101101 "
b10101101 8
b11011 #
b11011 7
1-
#1370
0-
#1375
b10101100 "
b10101100 8
b11100 #
b11100 7
1-
#1380
0-
#1385
b10101011 "
b10101011 8
b11101 #
b11101 7
1-
#1390
0-
#1395
b10101010 "
b10101010 8
b11110 #
b11110 7
1-
#1400
0-
#1405
b10101001 "
b10101001 8
b11111 #
b11111 7
1-
#1410
0-
#1415
b10101000 "
b10101000 8
b100000 #
b100000 7
1-
#1420
0-
#1425
b10100111 "
b10100111 8
b100001 #
b100001 7
1-
#1430
0-
#1435
b10100110 "
b10100110 8
b100010 #
b100010 7
1-
#1440
0-
#1445
b10100101 "
b10100101 8
b100011 #
b100011 7
1-
#1450
0-
#1455
b10100100 "
b10100100 8
b100100 #
b100100 7
1-
#1460
0-
#1465
b10100011 "
b10100011 8
b100101 #
b100101 7
1-
#1470
0-
#1475
b10100010 "
b10100010 8
b100110 #
b100110 7
1-
#1480
0-
#1485
b10100001 "
b10100001 8
b100111 #
b100111 7
1-
#1490
0-
#1495
b10100000 "
b10100000 8
b101000 #
b101000 7
1-
#1500
0-
#1505
b10011111 "
b10011111 8
b101001 #
b101001 7
1-
#1510
0-
#1515
b10011110 "
b10011110 8
b101010 #
b101010 7
1-
#1520
0-
#1525
b10011101 "
b10011101 8
b101011 #
b101011 7
1-
#1530
0-
#1535
b10011100 "
b10011100 8
b101100 #
b101100 7
1-
#1540
0-
#1545
b10011011 "
b10011011 8
b101101 #
b101101 7
1-
#1550
0-
#1555
b10011010 "
b10011010 8
b101110 #
b101110 7
1-
#1560
0-
#1565
b10011001 "
b10011001 8
b101111 #
b101111 7
1-
#1570
0-
#1575
b10011000 "
b10011000 8
b110000 #
b110000 7
1-
#1580
0-
#1585
b10010111 "
b10010111 8
b110001 #
b110001 7
1-
#1590
0-
#1595
b10010110 "
b10010110 8
b110010 #
b110010 7
1-
#1600
0-
#1605
b10010101 "
b10010101 8
b110011 #
b110011 7
1-
#1610
0-
#1615
b10010100 "
b10010100 8
b110100 #
b110100 7
1-
#1620
0-
#1625
b10010011 "
b10010011 8
b110101 #
b110101 7
1-
#1630
0-
#1635
b10010010 "
b10010010 8
b110110 #
b110110 7
1-
#1640
0-
#1645
b10010001 "
b10010001 8
b110111 #
b110111 7
1-
#1650
0-
#1655
b10010000 "
b10010000 8
b111000 #
b111000 7
1-
#1660
0-
#1665
b10001111 "
b10001111 8
b111001 #
b111001 7
1-
#1670
0-
#1675
b10001110 "
b10001110 8
b111010 #
b111010 7
1-
#1680
0-
#1685
b10001101 "
b10001101 8
b111011 #
b111011 7
1-
#1690
0-
#1695
b10001100 "
b10001100 8
b111100 #
b111100 7
1-
#1700
0-
#1705
b10001011 "
b10001011 8
b111101 #
b111101 7
1-
#1710
0-
#1715
b10001010 "
b10001010 8
b111110 #
b111110 7
1-
#1720
0-
#1725
b10001001 "
b10001001 8
b111111 #
b111111 7
1-
#1730
0-
#1735
b10001000 "
b10001000 8
b1000000 #
b1000000 7
1-
#1740
0-
#1745
b10000111 "
b10000111 8
b1000001 #
b1000001 7
1-
#1750
0-
#1755
b10000110 "
b10000110 8
b1000010 #
b1000010 7
1-
#1760
0-
#1765
b10000101 "
b10000101 8
b1000011 #
b1000011 7
1-
#1770
0-
#1775
b10000100 "
b10000100 8
b1000100 #
b1000100 7
1-
#1780
0-
#1785
b10000011 "
b10000011 8
b1000101 #
b1000101 7
1-
#1790
0-
#1795
b10000010 "
b10000010 8
b1000110 #
b1000110 7
1-
#1800
0-
#1805
b10000001 "
b10000001 8
b1000111 #
b1000111 7
1-
#1810
0-
#1815
b10000000 "
b10000000 8
b1001000 #
b1001000 7
1-
#1820
0-
#1825
b1111111 "
b1111111 8
b1001001 #
b1001001 7
1-
#1830
0-
#1835
b1111110 "
b1111110 8
b1001010 #
b1001010 7
1-
#1840
0-
#1845
b1111101 "
b1111101 8
b1001011 #
b1001011 7
1-
#1850
0-
#1855
b1111100 "
b1111100 8
b1001100 #
b1001100 7
1-
#1860
0-
#1865
b1111011 "
b1111011 8
b1001101 #
b1001101 7
1-
#1870
0-
#1875
b1111010 "
b1111010 8
b1001110 #
b1001110 7
1-
#1880
0-
#1885
b1111001 "
b1111001 8
b1001111 #
b1001111 7
1-
#1890
0-
#1895
b1111000 "
b1111000 8
b1010000 #
b1010000 7
1-
#1900
0-
#1905
b1110111 "
b1110111 8
b1010001 #
b1010001 7
1-
#1910
0-
#1915
b1110110 "
b1110110 8
b1010010 #
b1010010 7
1-
#1920
0-
#1925
b1110101 "
b1110101 8
b1010011 #
b1010011 7
1-
#1930
0-
#1935
b1110100 "
b1110100 8
b1010100 #
b1010100 7
1-
#1940
0-
#1945
b1110011 "
b1110011 8
b1010101 #
b1010101 7
1-
#1950
0-
#1955
b1110010 "
b1110010 8
b1010110 #
b1010110 7
1-
#1960
0-
#1965
b1110001 "
b1110001 8
b1010111 #
b1010111 7
1-
#1970
0-
#1975
b1110000 "
b1110000 8
b1011000 #
b1011000 7
1-
#1980
0-
#1985
b1101111 "
b1101111 8
b1011001 #
b1011001 7
1-
#1990
0-
#1995
b1101110 "
b1101110 8
b1011010 #
b1011010 7
1-
#2000
0-
#2005
b1101101 "
b1101101 8
b1011011 #
b1011011 7
1-
#2010
0-
#2015
b1101100 "
b1101100 8
b1011100 #
b1011100 7
1-
#2020
0-
#2025
b1101011 "
b1101011 8
b1011101 #
b1011101 7
1-
#2030
0-
#2035
b1101010 "
b1101010 8
b1011110 #
b1011110 7
1-
#2040
0-
#2045
b1101001 "
b1101001 8
b1011111 #
b1011111 7
1-
#2050
0-
#2055
b1101000 "
b1101000 8
b1100000 #
b1100000 7
1-
#2060
0-
#2065
b1100111 "
b1100111 8
b1100001 #
b1100001 7
1-
#2070
0-
#2075
b1100110 "
b1100110 8
b1100010 #
b1100010 7
1-
#2080
0-
#2085
b1100101 "
b1100101 8
b1100011 #
b1100011 7
1-
#2090
0-
#2095
b1100100 "
b1100100 8
b1100100 #
b1100100 7
1-
#2100
0-
#2105
b1100011 "
b1100011 8
b1100101 #
b1100101 7
1-
#2110
0-
#2115
b1100010 "
b1100010 8
b1100110 #
b1100110 7
1-
#2120
0-
#2125
b1100001 "
b1100001 8
b1100111 #
b1100111 7
1-
#2130
0-
#2135
b1100000 "
b1100000 8
b1101000 #
b1101000 7
1-
#2140
0-
#2145
b1011111 "
b1011111 8
b1101001 #
b1101001 7
1-
#2150
0-
#2155
b1011110 "
b1011110 8
b1101010 #
b1101010 7
1-
#2160
0-
#2165
b1011101 "
b1011101 8
b1101011 #
b1101011 7
1-
#2170
0-
#2175
b1011100 "
b1011100 8
b1101100 #
b1101100 7
1-
#2180
0-
#2185
b1011011 "
b1011011 8
b1101101 #
b1101101 7
1-
#2190
0-
#2195
b1011010 "
b1011010 8
b1101110 #
b1101110 7
1-
#2200
0-
#2205
b1011001 "
b1011001 8
b1101111 #
b1101111 7
1-
#2210
0-
#2215
b1011000 "
b1011000 8
b1110000 #
b1110000 7
1-
#2220
0-
#2225
b1010111 "
b1010111 8
b1110001 #
b1110001 7
1-
#2230
0-
#2235
b1010110 "
b1010110 8
b1110010 #
b1110010 7
1-
#2240
0-
#2245
b1010101 "
b1010101 8
b1110011 #
b1110011 7
1-
#2250
0-
#2255
b1010100 "
b1010100 8
b1110100 #
b1110100 7
1-
#2260
0-
#2265
b1010011 "
b1010011 8
b1110101 #
b1110101 7
1-
#2270
0-
#2275
b1010010 "
b1010010 8
b1110110 #
b1110110 7
1-
#2280
0-
#2285
b1010001 "
b1010001 8
b1110111 #
b1110111 7
1-
#2290
0-
#2295
b1010000 "
b1010000 8
b1111000 #
b1111000 7
1-
#2300
0-
#2305
b1001111 "
b1001111 8
b1111001 #
b1111001 7
1-
#2310
0-
#2315
b1001110 "
b1001110 8
b1111010 #
b1111010 7
1-
#2320
0-
#2325
b1001101 "
b1001101 8
b1111011 #
b1111011 7
1-
#2330
0-
#2335
b1001100 "
b1001100 8
b1111100 #
b1111100 7
1-
#2340
0-
#2345
b1001011 "
b1001011 8
b1111101 #
b1111101 7
1-
#2350
0-
#2355
b1001010 "
b1001010 8
b1111110 #
b1111110 7
1-
#2360
0-
#2365
b1001001 "
b1001001 8
b1111111 #
b1111111 7
1-
#2370
0-
#2375
b1001000 "
b1001000 8
b10000000 #
b10000000 7
1-
#2380
0-
#2385
b1000111 "
b1000111 8
b10000001 #
b10000001 7
1-
#2390
0-
#2395
b1000110 "
b1000110 8
b10000010 #
b10000010 7
1-
#2400
0-
#2405
b1000101 "
b1000101 8
b10000011 #
b10000011 7
1-
#2410
0-
#2415
b1000100 "
b1000100 8
b10000100 #
b10000100 7
1-
#2420
0-
#2425
b1000011 "
b1000011 8
b10000101 #
b10000101 7
1-
#2430
0-
#2435
b1000010 "
b1000010 8
b10000110 #
b10000110 7
1-
#2440
0-
#2445
b1000001 "
b1000001 8
b10000111 #
b10000111 7
1-
#2450
0-
#2455
b1000000 "
b1000000 8
b10001000 #
b10001000 7
1-
#2460
0-
#2465
b111111 "
b111111 8
b10001001 #
b10001001 7
1-
#2470
0-
#2475
b111110 "
b111110 8
b10001010 #
b10001010 7
1-
#2480
0-
#2485
b111101 "
b111101 8
b10001011 #
b10001011 7
1-
#2490
0-
#2495
b111100 "
b111100 8
b10001100 #
b10001100 7
1-
#2500
0-
#2505
b111011 "
b111011 8
b10001101 #
b10001101 7
1-
#2510
0-
#2515
b111010 "
b111010 8
b10001110 #
b10001110 7
1-
#2520
0-
#2525
b111001 "
b111001 8
b10001111 #
b10001111 7
1-
#2530
0-
#2535
b111000 "
b111000 8
b10010000 #
b10010000 7
1-
#2540
0-
#2545
b110111 "
b110111 8
b10010001 #
b10010001 7
1-
#2550
0-
#2555
b110110 "
b110110 8
b10010010 #
b10010010 7
1-
#2560
0-
#2565
b110101 "
b110101 8
b10010011 #
b10010011 7
1-
#2570
0-
#2575
b110100 "
b110100 8
b10010100 #
b10010100 7
1-
#2580
0-
#2585
b110011 "
b110011 8
b10010101 #
b10010101 7
1-
#2590
0-
#2595
b110010 "
b110010 8
b10010110 #
b10010110 7
1-
#2600
0-
#2605
b110001 "
b110001 8
b10010111 #
b10010111 7
1-
#2610
0-
#2615
b110000 "
b110000 8
b10011000 #
b10011000 7
1-
#2620
0-
#2625
b101111 "
b101111 8
b10011001 #
b10011001 7
1-
#2630
0-
#2635
b101110 "
b101110 8
b10011010 #
b10011010 7
1-
#2640
0-
#2645
b101101 "
b101101 8
b10011011 #
b10011011 7
1-
#2650
0-
#2655
b101100 "
b101100 8
b10011100 #
b10011100 7
1-
#2660
0-
#2665
b101011 "
b101011 8
b10011101 #
b10011101 7
1-
#2670
0-
#2675
b101010 "
b101010 8
b10011110 #
b10011110 7
1-
#2680
0-
#2685
b101001 "
b101001 8
b10011111 #
b10011111 7
1-
#2690
0-
#2695
b101000 "
b101000 8
b10100000 #
b10100000 7
1-
#2700
0-
#2705
b100111 "
b100111 8
b10100001 #
b10100001 7
1-
#2710
0-
#2715
b100110 "
b100110 8
b10100010 #
b10100010 7
1-
#2720
0-
#2725
b100101 "
b100101 8
b10100011 #
b10100011 7
1-
#2730
0-
#2735
b100100 "
b100100 8
b10100100 #
b10100100 7
1-
#2740
0-
#2745
b100011 "
b100011 8
b10100101 #
b10100101 7
1-
#2750
0-
#2755
b100010 "
b100010 8
b10100110 #
b10100110 7
1-
#2760
0-
#2765
b100001 "
b100001 8
b10100111 #
b10100111 7
1-
#2770
0-
#2775
b100000 "
b100000 8
b10101000 #
b10101000 7
1-
#2780
0-
#2785
b11111 "
b11111 8
b10101001 #
b10101001 7
1-
#2790
0-
#2795
b11110 "
b11110 8
b10101010 #
b10101010 7
1-
#2800
0-
#2805
b11101 "
b11101 8
b10101011 #
b10101011 7
1-
#2810
0-
#2815
b11100 "
b11100 8
b10101100 #
b10101100 7
1-
#2820
0-
#2825
b11011 "
b11011 8
b10101101 #
b10101101 7
1-
#2830
0-
#2835
b11010 "
b11010 8
b10101110 #
b10101110 7
1-
#2840
0-
#2845
b11001 "
b11001 8
b10101111 #
b10101111 7
1-
#2850
0-
#2855
b11000 "
b11000 8
b10110000 #
b10110000 7
1-
#2860
0-
#2865
b10111 "
b10111 8
b10110001 #
b10110001 7
1-
#2870
0-
#2875
b10110 "
b10110 8
b10110010 #
b10110010 7
1-
#2880
0-
#2885
b10101 "
b10101 8
b10110011 #
b10110011 7
1-
#2890
0-
#2895
b10100 "
b10100 8
b10110100 #
b10110100 7
1-
#2900
0-
#2905
b10011 "
b10011 8
b10110101 #
b10110101 7
1-
#2910
0-
#2915
b10010 "
b10010 8
b10110110 #
b10110110 7
1-
#2920
0-
#2925
b10001 "
b10001 8
b10110111 #
b10110111 7
1-
#2930
0-
#2935
b10000 "
b10000 8
b10111000 #
b10111000 7
1-
#2940
0-
#2945
b1111 "
b1111 8
b10111001 #
b10111001 7
1-
#2950
0-
#2955
b1110 "
b1110 8
b10111010 #
b10111010 7
1-
#2960
0-
#2965
b1101 "
b1101 8
b10111011 #
b10111011 7
1-
#2970
0-
#2975
b1100 "
b1100 8
b10111100 #
b10111100 7
1-
#2980
0-
#2985
b1011 "
b1011 8
b10111101 #
b10111101 7
1-
#2990
0-
#2995
b1010 "
b1010 8
b10111110 #
b10111110 7
1-
#3000
0-
#3005
b1001 "
b1001 8
b10111111 #
b10111111 7
1-
#3010
0-
#3015
b1000 "
b1000 8
b11000000 #
b11000000 7
1-
#3020
0-
#3025
b111 "
b111 8
b11000001 #
b11000001 7
1-
#3030
0-
#3035
b110 "
b110 8
b11000010 #
b11000010 7
1-
#3040
0-
#3045
b101 "
b101 8
b11000011 #
b11000011 7
1-
#3050
0-
